pyPelias/__init__.py
pyPelias-0.1.0.dist-info/METADATA
pyPelias-0.1.0.dist-info/WHEEL
pyPelias-0.1.0.dist-info/top_level.txt
pyPelias-0.1.0.dist-info/RECORD
