Metadata-Version: 2.1
Name: pyPelias
Version: 0.1.0
Summary: A simple python wrapper for the Pelias API for geocoding and reverse geocoding
Home-page: https://github.com/getorca/pyPelias
Author: Lawrence Stewart
Author-email: lawrence@lawrencestewart.ca
License: UNKNOWN
Platform: UNKNOWN
Classifier: Programming Language :: Python :: 3
Classifier: License :: OSI Approved :: MIT License
Classifier: Operating System :: OS Independent
